find_ip_to_db/__init__.py
find_ip_to_db/find_ip_to_db.py
dushyanth-1.0.4.dist-info/METADATA
dushyanth-1.0.4.dist-info/WHEEL
dushyanth-1.0.4.dist-info/top_level.txt
dushyanth-1.0.4.dist-info/RECORD
